XenonUI/__init__.py
XenonUI/XUIlib/ImageLibConfig.py
XenonUI/XUIlib/SystemInfo.py
XenonUI/XUIlib/__init__.py
XenonUI/XUIlib/imgtool.py
XenonUI/XUIlib/page.py
XenonUI/XUIlib/progress.py
XenonUI/XUIlib/image/A.py
XenonUI/XUIlib/image/B.py
XenonUI/XUIlib/image/C.py
XenonUI/XUIlib/image/D.py
XenonUI/XUIlib/image/E.py
XenonUI/XUIlib/image/F.py
XenonUI/XUIlib/image/G.py
XenonUI/XUIlib/image/H.py
XenonUI/XUIlib/image/I.py
XenonUI/XUIlib/image/J.py
XenonUI/XUIlib/image/K.py
XenonUI/XUIlib/image/L.py
XenonUI/XUIlib/image/M.py
XenonUI/XUIlib/image/N.py
XenonUI/XUIlib/image/O.py
XenonUI/XUIlib/image/P.py
XenonUI/XUIlib/image/Q.py
XenonUI/XUIlib/image/R.py
XenonUI/XUIlib/image/S.py
XenonUI/XUIlib/image/T.py
XenonUI/XUIlib/image/U.py
XenonUI/XUIlib/image/V.py
XenonUI/XUIlib/image/W.py
XenonUI/XUIlib/image/X.py
XenonUI/XUIlib/image/XUI.py
XenonUI/XUIlib/image/Y.py
XenonUI/XUIlib/image/Z.py
XenonUI/XUIlib/image/__init__.py
XenonUI/XUIlib/image/cpu.py
XenonUI/XUIlib/image/disk.py
XenonUI/XUIlib/image/ram.py
XenonUI/XUIlib/pages/Exit.py
XenonUI/XUIlib/pages/Help.py
XenonUI/XUIlib/pages/__init__.py
XenonUI-1.2.6.dist-info/LICENSE.txt
XenonUI-1.2.6.dist-info/METADATA
XenonUI-1.2.6.dist-info/WHEEL
XenonUI-1.2.6.dist-info/top_level.txt
XenonUI-1.2.6.dist-info/RECORD
