Metadata-Version: 2.1
Name: XenonUI
Version: 1.2.6
Summary: XUI is a page management GUI framework for python that is based on the platform-independent GUI package tinker.
Home-page: https://github.com/wacmkxiaoyi/Xenon-UI
Author: Junxiang Huang
Author-email: huangjunxiang@mail.ynu.edu.cn
Classifier: Programming Language :: Python :: 3
Classifier: License :: OSI Approved :: MIT License
Classifier: Operating System :: OS Independent
Requires-Python: >=3.6
License-File: LICENSE.txt
